[
	{
		"constant": true,
		"inputs": [],
		"name": "implementation",
		"outputs": [
			{
				"name": "",
				"type": "address"
			}
		],
		"payable": false,
		"stateMutability": "view",
		"type": "function"
	},
	{
		"constant": true,
		"inputs": [],
		"name": "nextOwner",
		"outputs": [
			{
				"name": "",
				"type": "address"
			}
		],
		"payable": false,
		"stateMutability": "view",
		"type": "function"
	},
	{
		"constant": true,
		"inputs": [],
		"name": "owner",
		"outputs": [
			{
				"name": "",
				"type": "address"
			}
		],
		"payable": false,
		"stateMutability": "view",
		"type": "function"
	},
	{
		"constant": true,
		"inputs": [],
		"name": "entered",
		"outputs": [
			{
				"name": "",
				"type": "bool"
			}
		],
		"payable": false,
		"stateMutability": "view",
		"type": "function"
	},
	{
		"constant": true,
		"inputs": [],
		"name": "WETH",
		"outputs": [
			{
				"name": "",
				"type": "address"
			}
		],
		"payable": false,
		"stateMutability": "view",
		"type": "function"
	},
	{
		"constant": false,
		"inputs": [
			{
				"name": "_newImp",
				"type": "address"
			}
		],
		"name": "_setImplementation",
		"outputs": [],
		"payable": false,
		"stateMutability": "nonpayable",
		"type": "function"
	},
	{
		"constant": true,
		"inputs": [],
		"name": "factory",
		"outputs": [
			{
				"name": "",
				"type": "address"
			}
		],
		"payable": false,
		"stateMutability": "view",
		"type": "function"
	},
	{
		"inputs": [
			{
				"name": "_implementation",
				"type": "address"
			},
			{
				"name": "_factory",
				"type": "address"
			},
			{
				"name": "_WETH",
				"type": "address"
			}
		],
		"payable": false,
		"stateMutability": "nonpayable",
		"type": "constructor"
	},
	{
		"payable": true,
		"stateMutability": "payable",
		"type": "fallback"
	}
]